faust_joins/__init__.py
faust_joins/joiner.py
faust_joins-0.1.3.dist-info/WHEEL
faust_joins-0.1.3.dist-info/METADATA
faust_joins-0.1.3.dist-info/RECORD
