Metadata-Version: 2.1
Name: faust-joins
Version: 0.1.3
Summary: Join Faust Streams
Home-page: https://github.com/BWStearns/faust_joins
License: MIT
Keywords: Faust,joins,kafka
Author: Brian Stearns
Author-email: brian.stearns@kensho.com
Requires-Python: >=3.6,<4.0
Classifier: License :: OSI Approved :: MIT License
Classifier: Programming Language :: Python :: 3
Classifier: Programming Language :: Python :: 3.6
Classifier: Programming Language :: Python :: 3.7
Classifier: Programming Language :: Python :: 3.8
Requires-Dist: faust (>=1.9.0,<2.0.0)
Project-URL: Documentation, https://github.com/BWStearns/faust_joins
Project-URL: Repository, https://github.com/BWStearns/faust_joins
Project-URL: issues, https://github.com/BWStearns/faust_joins/issues
